{
  "_fv": 39,
  "_type": "recipe",
  "definition": {
    "recipeType": "Crafting",
    "xpReward": 0.0,
    "cookingTime": 200,
    "recipeRetstackSize": 1,
    "group": "",
    "recipeShapeless": false,
    "recipeSlots": [
      {
        "value": "Blocks.GLASS"
      },
      {
        "value": "Blocks.GLASS"
      },
      {
        "value": "Blocks.GLASS"
      },
      {
        "value": "Blocks.LAPIS_BLOCK"
      },
      {
        "value": "CUSTOM:OrbWithoutMegaEvolution"
      },
      {
        "value": "Blocks.OBSIDIAN"
      },
      {
        "value": "Blocks.GLASS"
      },
      {
        "value": "Blocks.GLASS"
      },
      {
        "value": "Blocks.GLASS"
      }
    ],
    "recipeReturnStack": {
      "value": "CUSTOM:AshGreninja"
    },
    "name": "ash_greninja_recipe",
    "namespace": "mod"
  }
}